Metadata-Version: 2.3
Name: yta-audio-narration-coqui
Version: 0.0.3
Summary: Youtube Autonomous Audio Narration Coqui Voice Module.
Author: danialcala94
Author-email: danielalcalavalera@gmail.com
Requires-Python: ==3.9
Classifier: Programming Language :: Python :: 3
Classifier: Programming Language :: Python :: 3.9
Requires-Dist: coqui-tts (>=0.25.3,<0.26.0)
Requires-Dist: yta_audio_narration_common (>=0.0.1,<1.0.0)
Requires-Dist: yta_constants (>=0.0.1,<1.0.0)
Requires-Dist: yta_programming (>=0.0.1,<1.0.0)
